{
  "posts": [
    {
      "id": 1,
      "title": "Post One (Post 1)",
      "body": "This is Post 1"
    },
    {
      "id": 2,
      "title": "Post Two (Post 2)",
      "body": "This is Post 2"
    },
    {
      "id": 3,
      "title": "Post Three (Post 3)",
      "body": "This is Post 3"
    },
    {
      "id": 4,
      "title": "Post Four (Post 4)",
      "body": "This is Post 4"
    },
    {
      "id": 5,
      "title": "Post Five (Post 5)",
      "body": "This is Post 5"
    },
    {
      "id": 6
    },
    {
      "id": 7
    },
    {
      "id": 8
    },
    {
      "id": 9
    },
    {
      "id": 10
    },
    {
      "id": 11
    },
    {
      "id": 12
    },
    {
      "id": 13
    },
    {
      "id": 14
    },
    {
      "id": 15
    },
    {
      "id": 16
    },
    {
      "id": 17
    },
    {
      "id": 18
    },
    {
      "id": 19
    },
    {
      "id": 20
    },
    {
      "id": 21
    },
    {
      "id": 22
    },
    {
      "id": 23
    },
    {
      "id": 24
    },
    {
      "title": "Buggie",
      "body": "Test Contents",
      "id": 25
    },
    {
      "title": "Testing",
      "body": "Body....",
      "id": 26
    },
    {
      "title": "Another Post",
      "body": "Contents.....",
      "id": 27
    }
  ]
}